jaxonloader/__init__.py
jaxonloader/dataloader.py
jaxonloader/dataset.py
jaxonloader/utils.py
jaxonloader-0.9.1.dist-info/METADATA
jaxonloader-0.9.1.dist-info/WHEEL
jaxonloader-0.9.1.dist-info/licenses/LICENSE
jaxonloader-0.9.1.dist-info/RECORD
