Metadata-Version: 2.3
Name: jaxonloader
Version: 0.9.1
Summary: A dataloader, but for JAX/Numpy
Author-email: "Artur A. Galstyan" <mail@arturgalstyan.dev>
License: MIT License
License-File: LICENSE
Requires-Python: ~=3.10
Requires-Dist: beartype
Requires-Dist: jax
Requires-Dist: jaxlib
Requires-Dist: jaxtyping
Requires-Dist: typing-extensions
Provides-Extra: dev
Requires-Dist: mkdocs; extra == 'dev'
Requires-Dist: nox; extra == 'dev'
Requires-Dist: pre-commit; extra == 'dev'
Requires-Dist: pytest; extra == 'dev'
